espoem_facts
