Metadata-Version: 1.0
Name: espoem-facts
Version: 0.0.7
Summary: an @espoem fact bot on steem blockchain
Home-page: http://github.com/emre/espoem_facts
Author: emre yilmaz
Author-email: mail@emreyilmaz.me
License: MIT
Platform: UNKNOWN
